recipie/__init__.py
recipie/contextlib.py
recipie/functools.py
recipie-0.0.3.dist-info/LICENSE
recipie-0.0.3.dist-info/METADATA
recipie-0.0.3.dist-info/WHEEL
recipie-0.0.3.dist-info/top_level.txt
recipie-0.0.3.dist-info/RECORD
