Metadata-Version: 2.1
Name: recipie
Version: 0.0.3
Summary: Python idoms and recipes
Author: Harvey Pham
License: BSD 3-Clause License
Project-URL: Homepage, https://github.com/harveypham/recipie
Project-URL: Bug Tracker, https://github.com/harveypham/recipie/issues
Classifier: Programming Language :: Python :: 3
Classifier: Operating System :: OS Independent
Requires-Python: >=3.9
License-File: LICENSE
